SlySheets/__init__.py
SlySheets/__main__.py
SlySheets/sheets.py
SlySheets-0.2.3.dist-info/LICENSE
SlySheets-0.2.3.dist-info/METADATA
SlySheets-0.2.3.dist-info/WHEEL
SlySheets-0.2.3.dist-info/top_level.txt
SlySheets-0.2.3.dist-info/RECORD
