Metadata-Version: 2.1
Name: SlySheets
Version: 0.2.3
Summary: No-boilerplate, async and typed Google Sheets access.
Author: Dunkyl 🔣🔣
License: MIT License
Project-URL: Homepage, https://docs.dunkyl.net/SlySheets-Python/
Project-URL: Repository, https://github.com/dunkyl/SlySheets-Python
Project-URL: Documentation, https://docs.dunkyl.net/SlySheets-Python/
Project-URL: Bug Tracker, https://github.com/dunkyl/SlySheets-Python/issues
Classifier: Operating System :: OS Independent
Requires-Python: >=3.10
License-File: LICENSE
Requires-Dist: SlyAPI >=0.4.3
Requires-Dist: pytz
Provides-Extra: dev
Requires-Dist: pytest ; extra == 'dev'
Requires-Dist: pytest-asyncio ; extra == 'dev'
Requires-Dist: myst-parser ; extra == 'dev'
Requires-Dist: furo ; extra == 'dev'
Requires-Dist: sphinxcontrib-trio ; extra == 'dev'
Requires-Dist: sphinx-copybutton ; extra == 'dev'
Requires-Dist: sphinxext-opengraph ; extra == 'dev'
